{
    "version": 4,
    "configurePresets": [
      {
        "name": "debug",
        "displayName": "Debug and custom flags",
        "generator": "Ninja",
        "binaryDir": "${sourceDir}/build",
        "cacheVariables": {
          "CMAKE_BUILD_TYPE": "Debug",
          "CMAKE_C_COMPILER": "clang-17",
          "CMAKE_CXX_COMPILER": "clang++-17",
          "CMAKE_C_COMPILER_LAUNCHER": "ccache",
          "CMAKE_CXX_COMPILER_LAUNCHER": "ccache",
          "CMAKE_EXPORT_COMPILE_COMMANDS": "YES",
          "TT_RUNTIME_DEBUG": "ON",
          "TTMLIR_BUILD_TYPE": "Debug"
        },
        "cmakeExecutable": "sea_cmake"
      },
      {
        "name": "release",
        "displayName": "Release and custom flags",
        "generator": "Ninja",
        "binaryDir": "${sourceDir}/build",
        "cacheVariables": {
          "CMAKE_BUILD_TYPE": "Release",
          "CMAKE_C_COMPILER": "clang-17",
          "CMAKE_CXX_COMPILER": "clang++-17",
          "CMAKE_C_COMPILER_LAUNCHER": "ccache",
          "CMAKE_CXX_COMPILER_LAUNCHER": "ccache",
          "CMAKE_EXPORT_COMPILE_COMMANDS": "YES",
          "TTMLIR_BUILD_TYPE": "Release",
          "TT_RUNTIME_DEBUG": "OFF"
        },
        "cmakeExecutable": "sea_cmake"
      }
    ]
}
